{
    "runProverServer": false,
    "runProverServerMock": false,
    "runProverClient": false,

    "runExecutorServer": false,
    "runExecutorClient": false,
    "runExecutorClientMultithread": false,

    "runStateDBServer": false,
    "runStateDBTest": false,

    "runAggregatorServer": false,
    "runAggregatorClient": false,

    "runFileGenBatchProof": false,
    "runFileGenAggregatedProof": true,
    "runFileGenFinalProof": false,
    "runFileProcessBatch": false,
    "runFileProcessBatchMultithread": false,

    "runKeccakScriptGenerator": false,
    "runKeccakTest": false,
    "runStorageSMTest": false,
    "runBinarySMTest": false,
    "runMemAlignSMTest": false,

    "executeInParallel": true,
    "useMainExecGenerated": false,
    "saveRequestToFile": false,
    "saveInputToFile": false,
    "saveDbReadsToFile": false,
    "saveDbReadsToFileOnChange": false,
    "saveOutputToFile": false,
    "saveProofToFile": false,
    "saveResponseToFile": false,
    "loadDBToMemCache": true,
    "opcodeTracer": false,
    "logRemoteDbReads": false,
    "logExecutorServerResponses": false,

    "proverServerPort": 50051,
    "proverServerMockPort": 50052,
    "proverServerMockTimeout": 10000000,
    "proverClientPort": 50051,
    "proverClientHost": "127.0.0.1",

    "executorServerPort": 50071,
    "executorROMLineTraces": false,
    "executorClientPort": 50071,
    "executorClientHost": "127.0.0.1",

    "stateDBServerPort": 50061,
    "stateDBURL": "local",

    "aggregatorServerPort": 50081,
    "aggregatorClientPort": 50081,
    "aggregatorClientHost": "127.0.0.1",

    "inputFile": "aggregatedProof/zkevm.recursive2.zkin_01.proof.json",
    "inputFile2": "aggregatedProof/zkevm.recursive2.zkin_23.proof.json",
    "outputPath": "output",
    "rom": "rom.json",
    "zkevmCmPols_disabled": "zkevm.commit",
    "c12aCmPols": "zkevm.c12a.commit",
    "recursive1CmPols_disabled": "runtime/recursive1.commit",
    "recursive2CmPols_disabled": "runtime/recursive2.commit",
    "recursivefCmPols_disabled": "runtime/recursivef.commit",
    "finalCmPols_disabled": "runtime/final.commit",
    "zkevmConstPols": "config/zkevm/zkevm.const",
    "c12aConstPols": "config/c12a/zkevm.c12a.const",
    "recursive1ConstPols": "config/recursive1/recursive1.const",
    "recursive2ConstPols": "config/recursive2/recursive2.const",
    "mapConstPolsFile": false,
    "zkevmConstantsTree": "config/zkevm/zkevm.consttree",
    "c12aConstantsTree": "config/c12a/c12a.consttree",
    "recursive1ConstantsTree": "config/recursive1/recursive1.consttree",
    "recursive2ConstantsTree": "config/recursive2/recursive2.consttree",
    "recursivefConstantsTree": "config/recursivef/recursivef.consttree",
    "mapConstantsTreeFile": false,
    "recursive2StarkProof": "runtime/recursive2.proof.json",
    "recursivefStarkProof": "runtime/recursivef.proof.json",
    "recursive2StarkProofZkIn":"runtime/recursive2.zkin.proof.json",
    "recursivefStarkProofZkIn":"runtime/recursivef.zkin.proof.json",
    "finalVerkey":"config/final/final.verkey.json",
    "zkevmVerifier": "config/zkevm/verifier.dat",
    "recursive1Verifier": "config/zkevm/recursive1.verifier.dat",
    "recursive2Verifier": "config/recursive2/recursive2.verifier.dat",
    "recursivefVerifier": "config/recursivef/recursivef.verifier.dat",
    "finalVerifier": "config/final/final.verifier.dat",
    "recursive2Witness": "runtime/recursive2.witness.wtns",
    "recursivefWitness": "runtime/recursivef.witness.wtns",
    "finalWitness": "zkevm.final.witness.wtns",
    "c12aExec": "config/c12a/c12a.exec",
    "recursive1Exec": "config/recursive1/recursive1.exec",
    "recursive2Exec": "config/recursive2/recursive2.exec",
    "finalExec": "config/final/final.exec",
    "finalStarkZkey": "config/final/final.g16.0001.zkey",
    "publicsOutput": "runtime/public.json",
    
    "keccakScriptFile": "config/script/keccak_script.json",
    "storageRomFile": "config/scripts/storage_sm_rom.json",
     

    "proofFile": "proof.json",


    "zkevmStarkInfo": "config/zkevm/zkevm.starkinfo.json",
    "c12aStarkInfo": "config/c12a/c12a.starkinfo.json",
    "recursive1StarkInfo": "config/recursive1/recursive1.starkinfo.json",
    "recursive2StarkInfo": "config/recursive2/recursive2.starkinfo.json",
    
    "databaseURL": "local",
    "databaseURL_disabled": "postgresql://statedb:statedb@127.0.0.1:5432/testdb",
    "dbNodesTableName": "state.nodes",
    "dbProgramTableName": "state.program",
    "dbAsyncWrite": false,
    "cleanerPollingPeriod": 600,
    "requestsPersistence": 3600,
    "maxExecutorThreads": 20,
    "maxProverThreads": 8,
    "maxStateDBThreads": 8
}